eeg_auto_tools/ASSR.csv
eeg_auto_tools/ERSP.py
eeg_auto_tools/__init__.py
eeg_auto_tools/clean.py
eeg_auto_tools/craft_events.py
eeg_auto_tools/developments.py
eeg_auto_tools/metrics.py
eeg_auto_tools/model_params.json
eeg_auto_tools/models.py
eeg_auto_tools/montages.py
eeg_auto_tools/quality_check.py
eeg_auto_tools/savers.py
eeg_auto_tools/scenarious.py
eeg_auto_tools/transforms.py
eeg_auto_tools-0.0.49.dist-info/licenses/LICENSE
eeg_auto_tools-0.0.49.dist-info/METADATA
eeg_auto_tools-0.0.49.dist-info/WHEEL
eeg_auto_tools-0.0.49.dist-info/top_level.txt
eeg_auto_tools-0.0.49.dist-info/RECORD
