Metadata-Version: 2.4
Name: eeg_auto_tools
Version: 0.0.49
Summary: The set of tools for working with EEG data
Author-email: Sear <vasilijkrukovskij2015@gmail.com>
License: 
License-File: LICENSE
Requires-Dist: cmake==3.31.6
Requires-Dist: numba==0.59.1
Requires-Dist: llvmlite==0.42
Requires-Dist: autoreject==0.4.3
Requires-Dist: emd==0.7.0
Requires-Dist: joblib==1.4.2
Requires-Dist: matplotlib==3.10.1
Requires-Dist: mne==1.9.0
Requires-Dist: mne_icalabel==0.7.0
Requires-Dist: networkx==3.4.2
Requires-Dist: numpy==1.26.4
Requires-Dist: pandas==2.2.3
Requires-Dist: python-dotenv==1.0.1
Requires-Dist: scikit_learn==1.6.1
Requires-Dist: scipy==1.15.2
Requires-Dist: seaborn==0.13.2
Requires-Dist: torch==2.5.1
Requires-Dist: tqdm==4.66.5
Dynamic: license-file
